ptlib/__init__.py
ptlib/_backend.py
ptlib/_typing.py
ptlib/core/__init__.py
ptlib/core/_backend.py
ptlib/core/api.py
ptlib/core/common.py
ptlib/core/controller.py
ptlib/core/job.py
ptlib/core/metadata.py
ptlib/core/queue.py
ptlib/core/task.py
ptlib/core/worker.py
ptlib/errors/__init__.py
ptlib/utils/__init__.py
ptlib/utils/diagram.py
ptlib-0.0.5.dist-info/LICENSE
ptlib-0.0.5.dist-info/METADATA
ptlib-0.0.5.dist-info/WHEEL
ptlib-0.0.5.dist-info/top_level.txt
ptlib-0.0.5.dist-info/RECORD
