Metadata-Version: 2.1
Name: ptlib
Version: 0.0.5
Summary: This library aims to provide efficient implementation and detaile debugging of solutions to problems in the asynchronous domain.
Home-page: https://github.com/jfw225/ptlib
Author: Joseph Whelan
Author-email: 
License: UNKNOWN
Project-URL: Bug Tracker, https://github.com/jfw225/ptlib/issues
Platform: UNKNOWN
Classifier: Programming Language :: Python :: 3
Classifier: License :: OSI Approved :: MIT License
Classifier: Operating System :: OS Independent
Requires-Python: >=3.8
License-File: LICENSE
Requires-Dist: numpy (>=1.19.5)
Requires-Dist: matplotlib (>=3.4.3)
